[
  {
    "type":"monstergroup",
    "name" : "GROUP_ROBOT",
    "override": false,
    "auto_total": true,
    "default" : "mon_manhack",
    "monsters" : [
      { "monster" : "mon_tripod", "freq" : 110, "cost_multiplier" : 0 },
      { "monster" : "mon_chickenbot", "freq" : 60, "cost_multiplier" : 0 },
	  { "monster" : "mon_met", "freq" : 90, "cost_multiplier" : 0 },
      { "monster" : "mon_sniper", "freq" : 70, "cost_multiplier" : 0 },
      { "monster" : "mon_tankbot", "freq" : 20, "cost_multiplier" : 0 }
    ]
  }
]



