[
  {
    "id": "gc166mag",
    "type": "MAGAZINE",
    "name": { "str": "GC166 Magazine" },
    "description": "A 120-round horizontal helical magazine which fits in the frame of the GC166 Gauss Carbine.",
    "weight": "22 g",
    "volume": "500 ml",
    "price": "40 USD",
    "material": [ "plastic" ],
    "symbol": "#",
    "color": "light_gray",
    "ammo_type": "magpin",
    "capacity": 120,
    "reliability": 7,
    "reload_time": 200,
    "looks_like": "calicomag",
    "flags": [ "MAG_COMPACT" ]
  }
]
