[
  {
    "result": "seed_radcorn",
    "type": "recipe",
    "category": "CC_FOOD",
    "subcategory": "CSC_FOOD_SEEDS",
    "skill_used": "survival",
    "difficulty": 4,
    "time": "5 m",
    "autolearn": true,
    "qualities": [ { "id": "CUT", "level": 1 } ],
    "components": [ [ [ "radcorn", 1 ] ] ],
    "flags": [ "ALLOW_ROTTEN" ]
  },
  
  {
    "type": "recipe",
    "result": "radcorn_cooked",
    "category": "CC_FOOD",
    "subcategory": "CSC_FOOD_VEGGI",
    "skill_used": "cooking",
    "time": "4 m",
    "autolearn": true,
    "qualities": [ { "id": "COOK", "level": 1 } ],
    "tools": [ [ [ "surface_heat", 5, "LIST" ] ] ],
    "components": [ [ [ "radcorn", 1 ] ] ]
  },
  
  {
    "type": "recipe",
    "result": "dry_radcorn",
    "charges": 1,
    "category": "CC_FOOD",
    "subcategory": "CSC_FOOD_DRY",
    "skill_used": "cooking",
    "difficulty": 2,
    "time": "18 m",
    "autolearn": true,
    "batch_time_factors": [ 67, 5 ],
    "tools": [ [ [ "dehydrator", 25 ], [ "char_smoker", 25 ] ] ],
    "components": [
      [ [ "radcorn", 1 ] ]
    ]
  },
  
  {
    "type": "recipe",
    "result": "radcorn_canned",
    "id_suffix": "jarred",
    "byproducts": [ [ "water", 10 ] ],
    "container": "jar_glass_sealed",
    "category": "CC_FOOD",
    "subcategory": "CSC_FOOD_VEGGI",
    "skill_used": "cooking",
    "difficulty": 4,
    "time": "30 m",
    "result_mult": 2,
    "book_learn": [ [ "cookbook", 4 ], [ "manual_canning", 3 ] ],
    "batch_time_factors": [ 83, 5 ],
    "qualities": [ { "id": "CUT", "level": 1 }, { "id": "COOK", "level": 3 } ],
    "tools": [ [ [ "surface_heat", 100, "LIST" ] ], [ [ "pot_canning", -1 ] ] ],
    "components": [
      [ [ "water", 11 ], [ "water_clean", 11 ] ],
      [ [ "jar_glass", 1 ] ],
      [ [ "radcorn", 4 ] ]
    ]
  },
  
  
  {
    "type": "recipe",
    "result": "radcorn_pickled",
    "id_suffix": "jarred",
    "container": "jar_glass_sealed",
    "category": "CC_FOOD",
    "subcategory": "CSC_FOOD_VEGGI",
    "skill_used": "cooking",
    "difficulty": 5,
    "time": "30 m",
    "result_mult": 2,
    "book_learn": [ [ "manual_canning", 4 ] ],
    "batch_time_factors": [ 83, 5 ],
    "qualities": [ { "id": "CUT", "level": 1 }, { "id": "COOK", "level": 3 } ],
    "tools": [ [ [ "surface_heat", 20, "LIST" ] ] ],
    "components": [
      [ [ "water", 1 ], [ "water_clean", 1 ], [ "salt_water", 1 ], [ "saline", 5 ] ],
      [ [ "jar_glass", 1 ] ],
      [
        [ "radcorn", 2 ]
      ],
      [ [ "vinegar", 1 ] ]
    ]
  },


  {
    "type": "recipe",
    "result": "radcorn_salted",
    "id_suffix": "vacuum_packed",
    "container": "plastic_bag_vac",
    "category": "CC_FOOD",
    "subcategory": "CSC_FOOD_VEGGI",
    "skill_used": "cooking",
    "difficulty": 4,
    "charges": 2,
    "time": "5 m",
    "batch_time_factors": [ 10, 3 ],
    "autolearn": true,
    "qualities": [ { "id": "CUT", "level": 1 }, { "id": "COOK", "level": 3 } ],
    "tools": [ [ [ "vac_sealer", 10 ], [ "makeshift_sealer", 20 ] ] ],
    "components": [ [ [ "bag_plastic", 1 ] ], [ [ "radcorn", 2] ], [ [ "salt_preservation", 2, "LIST" ] ] ]
  }

]