[
  {
    "id": "osrs_gold_piece",
	"looks_like": "coin_quarter",
    "type": "AMMO",
    "category": "other",
	"ammo_type": "osrs_gp",
    "name": { "str": "GP", "str_pl": "GP" },
    "description": "Lovely money!",
    "weight": 0,
    "price": 100,
    "material": [ "gold" ],
    "symbol": "o",
    "color": "yellow",
    "use_action": "COIN_FLIP"
  },
  {
    "id": "osrs_money_pouch",
    "type": "ARMOR",
    "name": { "str": "money pouch", "str_pl": "money pouches" },
    "description": "A small pouch that can be used to store your precious gold!",
    "weight": "0 g",
    "rigid": true,
    "price": 0,
    "to_hit": 1,
    "bashing": 1,
    "material": [ "leather" ],
    "symbol": "[",
    "looks_like": "leather_pouch",
    "color": "brown",
    "covers": [ "TORSO" ],
    "coverage": 1,
    "encumbrance": 0,
    "material_thickness": 1,
    "use_action": {
      "type": "bandolier",
      "capacity": 9999999,
      "ammo": [
        "osrs_gp"
      ],
      "draw_cost": 0
    },
    "flags": [ "WAIST", "OVERSIZE", "WATER_FRIENDLY" ]
  },
  {
    "id": "osrs_bolt_box",
    "type": "ARMOR",
    "name": { "str": "bolt box", "str_pl": "bolt boxes" },
    "description": "A leather box that can be used to store your bolts!",
    "weight": "0 g",
    "rigid": true,
    "price": 0,
    "to_hit": 1,
    "bashing": 1,
    "material": [ "leather" ],
    "symbol": "[",
    "looks_like": "leather_pouch",
    "color": "brown",
    "covers": [ "TORSO" ],
    "coverage": 1,
    "encumbrance": 0,
    "material_thickness": 1,
    "use_action": {
      "type": "bandolier",
      "capacity": 250,
      "ammo": [
        "osrs_bolt"
      ],
      "draw_cost": 50
    },
    "flags": [ "WAIST", "OVERSIZE" ]
  },
  {
    "type": "GENERIC",
    "id": "osrs_crossbow_string",
    "symbol": "/",
    "color": "white",
    "name": "crossbow string",
    "description": "A string for a crossbow.",
    "category": "other",
    "price": 400,
    "price_postapoc": 1200,
    "material": "wood",
    "weight": "2 g",
    "volume": "0 L"
  },
  {
    "id": "osrs_spade",
	"looks_like": "shovel",
    "type": "TOOL",
    "name": "spade",
    "description": "A slightly muddy spade.",
    "weight": "1800 g",
    "volume": "3500 ml",
    "price": 14600,
    "material": [ "steel", "wood" ],
    "symbol": "/",
    "color": "brown",
    "qualities": [ [ "DIG", 3 ] ]
  },
  {
    "id": "osrs_tinderbox",
	"looks_like": "tinderbox",
    "type": "TOOL",
    "name": { "str": "tinderbox", "str_pl": "tinderboxes" },
    "description": "Useful for lighting a fire.",
    "weight": "35 g",
    "volume": "250 ml",
    "price": 3700,
    "to_hit": -1,
    "material": [ "cardboard" ],
    "symbol": ",",
    "color": "light_gray",
    "use_action": { "type": "firestarter", "moves": 1000, "moves_slow": 5000 },
    "flags": [ "FIRESTARTER" ]
  },
  {
    "id": "osrs_manual_recipes_misc",
	"looks_like": "manual_fabrication",
    "type": "BOOK",
    "name": { "str": "Noob's Guide to Crafting", "str_pl": "copies of Noob's Guide to Crafting" },
    "description": "A large, hardback book detailing several items that can be made with ease.",
    "weight": "510 g",
    "volume": "750 ml",
    "price": 0,
    "price_postapoc": 0,
    "material": [ "paper" ],
    "symbol": "?",
    "color": "green",
    "skill": "fabrication",
    "max_level": 3,
    "intelligence": 5,
    "time": "30 m"
  },
  {
    "id": "osrs_manual_recipes_bronze",
	"looks_like": "manual_fabrication",
    "type": "BOOK",
    "name": { "str": "Noob's Guide to Bronze Crafting", "str_pl": "copies of Noob's Guide to Bronze Crafting" },
    "description": "A large, hardback book detailing several items that can be made with bronze, wood, and oak.",
    "weight": "510 g",
    "volume": "750 ml",
    "price": 0,
    "price_postapoc": 0,
    "material": [ "paper" ],
    "symbol": "?",
    "color": "green",
    "skill": "fabrication",
    "max_level": 3,
    "intelligence": 5,
    "time": "30 m"
  },
  {
    "id": "osrs_manual_recipes_iron",
	"looks_like": "manual_fabrication",
    "type": "BOOK",
    "name": { "str": "Noob's Guide to Iron Crafting", "str_pl": "copies of Noob's Guide to Iron Crafting" },
    "description": "A large, hardback book detailing several items that can be made with iron and willow.",
    "weight": "510 g",
    "volume": "750 ml",
    "price": 0,
    "price_postapoc": 0,
    "material": [ "paper" ],
    "symbol": "?",
    "color": "green",
    "skill": "fabrication",
    "max_level": 3,
    "intelligence": 5,
    "time": "30 m"
  },
  {
    "id": "osrs_manual_recipes_mithril",
	"looks_like": "manual_fabrication",
    "type": "BOOK",
    "name": { "str": "Noob's Guide to Mithril Crafting", "str_pl": "copies of Noob's Guide to Mithril Crafting" },
    "description": "A large, hardback book detailing several items that can be made with mithril and maple.",
    "weight": "510 g",
    "volume": "750 ml",
    "price": 0,
    "price_postapoc": 0,
    "material": [ "paper" ],
    "symbol": "?",
    "color": "green",
    "skill": "fabrication",
    "max_level": 3,
    "intelligence": 5,
    "time": "30 m"
  },
  {
    "id": "osrs_manual_recipes_adamant",
	"looks_like": "manual_fabrication",
    "type": "BOOK",
    "name": { "str": "Noob's Guide to Adamant Crafting", "str_pl": "copies of Noob's Guide to Adamant Crafting" },
    "description": "A large, hardback book detailing several items that can be made with adamantite and mahogany.",
    "weight": "510 g",
    "volume": "750 ml",
    "price": 0,
    "price_postapoc": 0,
    "material": [ "paper" ],
    "symbol": "?",
    "color": "green",
    "skill": "fabrication",
    "max_level": 3,
    "intelligence": 5,
    "time": "30 m"
  },
  {
    "id": "osrs_manual_recipes_runite",
	"looks_like": "manual_fabrication",
    "type": "BOOK",
    "name": { "str": "Noob's Guide to Runite Crafting", "str_pl": "copies of Noob's Guide to Runite Crafting" },
    "description": "A large, hardback book detailing several items that can be made with runite and yew.",
    "weight": "510 g",
    "volume": "750 ml",
    "price": 0,
    "price_postapoc": 0,
    "material": [ "paper" ],
    "symbol": "?",
    "color": "green",
    "skill": "fabrication",
    "max_level": 3,
    "intelligence": 5,
    "time": "30 m"
  }
]