[
  {
    "type": "recipe",
    "result": "pd_printing_9mm_printer",
    "category": "CC_WEAPON",
    "subcategory": "CSC_WEAPON_RANGED",
    "skill_used": "fabrication",
    "difficulty": 1,
    "time": "10 t",
    "reversible": false,
    "autolearn": true,
    "book_learn": [
      [ "pd_binder", 1, "Private 9 via 3D printer" ]
    ],
    "tools": [
      [ 
        [ "pd_binder",  -1 ],
        [ "pd_9mm_cad", -1 ]
      ]
    ],
    "components": [
      [ [ "3d_printer",    1 ] ],
      [ [ "plastic_chunk", 2 ] ],
      [ [ "chunk_polymer", 1 ] ]
    ]
  },
  {
    "type": "recipe",
    "result": "pd_printing_357_printer",
    "category": "CC_WEAPON",
    "subcategory": "CSC_WEAPON_RANGED",
    "skill_used": "fabrication",
    "difficulty": 1,
    "time": "10 t",
    "reversible": false,
    "autolearn": true,
    "book_learn": [
      [ "pd_binder", 1, "Private 357 via 3D printer" ]
    ],
    "tools": [
      [ 
        [ "pd_binder",  -1 ],
        [ "pd_357_cad", -1 ]
      ]
    ],
    "components": [
      [ [ "3d_printer",    1 ] ],
      [ [ "plastic_chunk", 2 ] ],
      [ [ "chunk_polymer", 1 ] ]
    ]
  },
  {
    "type": "recipe",
    "result": "pd_printing_45_printer",
    "category": "CC_WEAPON",
    "subcategory": "CSC_WEAPON_RANGED",
    "skill_used": "fabrication",
    "difficulty": 1,
    "time": "10 t",
    "reversible": false,
    "autolearn": true,
    "book_learn": [
      [ "pd_binder", 1, "Private 45 via 3D printer" ]
    ],
    "tools": [
      [
        [ "pd_binder",  -1 ],
        [ "pd_45_cad",  -1 ]
      ]
    ],
    "components": [
      [ [ "3d_printer",    1 ] ],
      [ [ "plastic_chunk", 2 ] ],
      [ [ "chunk_polymer", 1 ] ]
    ]
  },
  {
    "type": "recipe",
    "result": "pd_printing_mp5_printer",
    "category": "CC_WEAPON",
    "subcategory": "CSC_WEAPON_RANGED",
    "skill_used": "fabrication",
    "difficulty": 1,
    "time": "10 t",
    "reversible": false,
    "autolearn": true,
    "book_learn": [
      [ "pd_binder", 1, "Private 5 via 3D printer" ]
    ],
    "tools": [
      [
        [ "pd_binder",    -1 ],
        [ "pd_mp5_cad",   -1 ]
      ]
    ],
    "components": [
      [ [ "3d_factory",    1 ] ],
      [ [ "plastic_chunk", 5 ] ],
      [ [ "chunk_polymer", 2 ] ]
    ]
  },
  {
    "type": "recipe",
    "result": "pd_printing_mac10_printer",
    "category": "CC_WEAPON",
    "subcategory": "CSC_WEAPON_RANGED",
    "skill_used": "fabrication",
    "difficulty": 1,
    "time": "10 t",
    "reversible": false,
    "autolearn": true,
    "book_learn": [
      [ "pd_binder", 1, "Private 10 via 3D printer" ]
    ],
    "tools": [
      [
        [ "pd_binder",    -1 ],
        [ "pd_mac10_cad", -1 ]
      ]
    ],
    "components": [
      [ [ "3d_factory",    1 ] ],
      [ [ "plastic_chunk", 4 ] ],
      [ [ "chunk_polymer", 2 ] ]
    ]
  },
  {
    "type": "recipe",
    "result": "pd_printing_uzi_printer",
    "category": "CC_WEAPON",
    "subcategory": "CSC_WEAPON_RANGED",
    "skill_used": "fabrication",
    "difficulty": 1,
    "time": "10 t",
    "reversible": false,
    "autolearn": true,
    "book_learn": [
      [ "pd_binder", 1, "Private U via 3D printer" ]
    ],
    "tools": [
      [
        [ "pd_binder",    -1 ],
        [ "pd_uzi_cad",   -1 ]
      ]
    ],
    "components": [
      [ [ "3d_factory",    1 ] ],
      [ [ "plastic_chunk", 5 ] ],
      [ [ "chunk_polymer", 2 ] ]
    ]
  },
  {
    "type": "recipe",
    "result": "pd_printing_223_printer",
    "category": "CC_WEAPON",
    "subcategory": "CSC_WEAPON_RANGED",
    "skill_used": "fabrication",
    "difficulty": 1,
    "time": "10 t",
    "reversible": false,
    "autolearn": true,
    "book_learn": [
      [ "pd_binder", 1, "Private 223 via 3D printer" ]
    ],
    "tools": [
      [ 
        [ "pd_binder",  -1 ],
        [ "pd_223_cad", -1 ]
      ]
    ],
    "components": [
      [ [ "3d_printer",    1 ] ],
      [ [ "plastic_chunk", 8 ] ],
      [ [ "chunk_polymer", 3 ] ]
    ]
  },
  {
    "type": "recipe",
    "result": "pd_printing_3006_printer",
    "category": "CC_WEAPON",
    "subcategory": "CSC_WEAPON_RANGED",
    "skill_used": "fabrication",
    "difficulty": 1,
    "time": "10 t",
    "reversible": false,
    "autolearn": true,
    "book_learn": [
      [ "pd_binder", 1, "Private 3006 via 3D printer" ]
    ],
    "tools": [
      [
        [ "pd_binder",   -1 ],
        [ "pd_3006_cad", -1 ]
      ]
    ],
    "components": [
      [ [ "3d_printer",     1 ] ],
      [ [ "plastic_chunk", 14 ] ],
      [ [ "chunk_polymer",  4 ] ]
    ]
  },
  {
    "type": "recipe",
    "result": "pd_printing_pd12_printer",
    "category": "CC_WEAPON",
    "subcategory": "CSC_WEAPON_RANGED",
    "skill_used": "fabrication",
    "difficulty": 1,
    "time": "10 t",
    "reversible": false,
    "autolearn": true,
    "book_learn": [
      [ "pd_binder", 1, "Private 12 via 3D printer" ]
    ],
    "tools": [
      [
        [ "pd_binder", -1 ],
        [ "pd_12_cad", -1 ]
      ]
    ],
    "components": [
      [ [ "3d_printer",    1 ] ],
      [ [ "plastic_chunk", 2 ] ]
    ]
  }
]